sqlactive/__init__.py
sqlactive/active_record.py
sqlactive/async_query.py
sqlactive/base_model.py
sqlactive/conn.py
sqlactive/definitions.py
sqlactive/exceptions.py
sqlactive/inspection.py
sqlactive/serialization.py
sqlactive/session.py
sqlactive/smart_query.py
sqlactive/timestamp.py
sqlactive/types.py
sqlactive/utils.py
sqlactive-0.3.6.dist-info/licenses/LICENSE
sqlactive-0.3.6.dist-info/METADATA
sqlactive-0.3.6.dist-info/WHEEL
sqlactive-0.3.6.dist-info/top_level.txt
sqlactive-0.3.6.dist-info/RECORD
