Metadata-Version: 2.4
Name: sqlactive
Version: 0.3.6
Summary: SQLActive is a lightweight and asynchronous ActiveRecord-style wrapper for SQLAlchemy. Bring Django-like queries, automatic timestamps, nested eager loading, and serialization/deserialization for SQLAlchemy models.
Author-email: Dairo Mosquera <dairoandres123@gmail.com>
Project-URL: Homepage, https://github.com/daireto/sqlactive
Project-URL: Documentation, https://daireto.github.io/sqlactive/
Project-URL: Issues, https://github.com/daireto/sqlactive/issues
Project-URL: Repository, https://github.com/daireto/sqlactive
Keywords: sqlalchemy,active record,activerecord,orm,django-like,django queries,eager load,timestamps,serialization
Classifier: Programming Language :: Python :: 3.10
Classifier: Programming Language :: Python :: 3.11
Classifier: Programming Language :: Python :: 3.12
Classifier: Programming Language :: Python :: 3.13
Classifier: Programming Language :: Python :: 3.14
Classifier: License :: OSI Approved :: MIT License
Classifier: Operating System :: OS Independent
Classifier: Intended Audience :: Developers
Classifier: Topic :: Database
Requires-Python: >=3.10
License-File: LICENSE
Requires-Dist: sqlalchemy<3.0.0,>=2.0.0
Requires-Dist: deprecated<2.0.0,>=1.2.18
Requires-Dist: typing-extensions>=4.12.2
Dynamic: license-file
